{
  "一": "イチ・ひと(つ)",
  "二": "ニ・ふた",
  "三": "サン・み",
  "四": "シ・よ",
  "五": "ゴ・いつ",
  "六": "ロク・む",
  "七": "シチ・なな",
  "八": "ハチ・や",
  "九": "キュウ・ここの",
  "十": "ジュウ・とお",
  "百": "ヒャク・もも",
  "千": "セン・ち",
  "万": "マン・よろず",
  "円": "エン・まる(い)",
  "日": "ニチ・ひ",
  "月": "ゲツ・つき",
  "火": "カ・ひ",
  "水": "スイ・みず",
  "木": "ボク・き",
  "金": "キン・かね",
  "土": "ド・つち",
  "年": "ネン・とし",
  "時": "ジ・とき",
  "分": "ブン・わ(ける)",
  "半": "ハン・なか(ば)",
  "今": "コン・いま",
  "前": "ゼン・まえ",
  "後": "ゴ・のち",
  "午": "ゴ・うま",
  "間": "カン・あいだ",
  "毎": "マイ・ごと",
  "上": "ジョウ・うえ",
  "下": "カ・した",
  "中": "チュウ・なか",
  "左": "サ・ひだり",
  "右": "ウ・みぎ",
  "東": "トウ・ひがし",
  "西": "セイ・にし",
  "南": "ナン・みなみ",
  "北": "ホク・きた",
  "外": "ガイ・そと",
  "大": "ダイ・おお(きい)",
  "小": "ショウ・ちい(さい)",
  "高": "コウ・たか(い)",
  "長": "チョウ・なが(い)",
  "新": "シン・あたら(しい)",
  "古": "コ・ふる(い)",
  "白": "ハク・しろ",
  "人": "ジン・ひと",
  "男": "ダン・おとこ",
  "女": "ジョ・おんな",
  "子": "シ・こ",
  "父": "フ・ちち",
  "母": "ボ・はは",
  "友": "ユウ・とも",
  "先": "セン・さき",
  "生": "セイ・い(きる)",
  "名": "メイ・な",
  "学": "ガク・まな(ぶ)",
  "校": "コウ",
  "本": "ホン・もと",
  "語": "ゴ・かた(る)",
  "国": "コク・くに",
  "山": "サン・やま",
  "川": "セン・かわ",
  "田": "デン・た",
  "天": "テン・あまつ",
  "気": "キ・いき",
  "雨": "ウ・あめ",
  "花": "カ・はな",
  "空": "クウ・そら",
  "目": "モク・め",
  "耳": "ジ・みみ",
  "口": "コウ・くち",
  "手": "シュ・て",
  "足": "ソク・あし",
  "力": "リョク・ちから",
  "行": "コウ・い(く)",
  "来": "ライ・く(る)",
  "帰": "キ・かえ(る)",
  "見": "ケン・み(る)",
  "聞": "ブン・き(く)",
  "食": "ショク・く(う)",
  "買": "バイ・か(う)",
  "読": "ドク・よ(む)",
  "書": "ショ・か(く)",
  "話": "ワ・はな(す)",
  "言": "ゲン・い(う)",
  "出": "シュツ・で(る)",
  "入": "ニュウ・い(る)",
  "立": "リツ・た(つ)",
  "休": "キュウ・やす(む)",
  "会": "カイ・あ(う)",
  "車": "シャ・くるま",
  "電": "デン",
  "何": "カ・なに",
  "文": "ブン・ふみ",
  "音": "オン・おと",
  "少": "ショウ・すく(ない)",
  "多": "タ・おお(い)",
  "早": "ソウ・はや(い)",
  "引": "イン・ひ(く)",
  "映": "エイ・うつ(る)",
  "楽": "ガク・たの(しい)",
  "料": "リョウ",
  "建": "ケン・た(てる)",
  "験": "ケン・あかし",
  "洗": "セン・あら(う)",
  "台": "ダイ・うてな",
  "貸": "タイ・か(す)",
  "借": "シャク・か(りる)",
  "変": "ヘン・か(わる)",
  "閉": "ヘイ・と(じる)",
  "声": "セイ・こえ",
  "科": "カ",
  "束": "ソク・たば",
  "領": "リョウ・えり",
  "保": "ホ・たも(つ)",
  "歴": "レキ",
  "環": "カン・わ",
  "宇": "ウ",
  "宙": "チュウ",
  "宗": "シュウ・むね",
  "師": "シ・いくさ",
  "浅": "セン・あさ(い)",
  "岩": "ガン・いわ",
  "顔": "ガン・かお",
  "怖": "フ・こわ(い)",
  "恐": "キョウ・おそ(れる)",
  "恋": "レン・こ(う)",
  "労": "ロウ・ろう(する)",
  "液": "エキ",
  "眠": "ミン・ねむ(る)",
  "夢": "ム・ゆめ",
  "可": "カ",
  "与": "ヨ・あた(える)",
  "富": "フ・と(む)",
  "豊": "ホウ・ゆた(か)",
  "貧": "ヒン・まず(しい)",
  "乏": "ボウ・とぼ(しい)",
  "困": "コン・こま(る)",
  "易": "エキ・やさ(しい)",
  "簡": "カン・えら(ぶ)",
  "択": "タク・えら(ぶ)",
  "依": "イ・よ(る)",
  "利": "リ・き(く)",
  "貯": "チョ・た(める)",
  "払": "フツ・はら(う)",
  "域": "イキ",
  "席": "セキ・むしろ",
  "令": "レイ",
  "刷": "サツ・す(る)",
  "刊": "カン",
  "巻": "カン・ま(く)",
  "冊": "サツ・ふみ",
  "編": "ヘン・あ(む)",
  "訳": "ヤク・わけ",
  "翻": "ホン・ひるがえ(る)",
  "罰": "バツ・ばっ(する)",
  "捕": "ホ・と(らえる)",
  "逮": "タイ",
  "留": "リュウ・と(める)",
  "及": "キュウ・およ(ぶ)",
  "衆": "シュウ・おお(い)",
  "均": "キン・なら(す)",
  "録": "ロク・しる(す)",
  "抜": "バツ・ぬ(く)",
  "副": "フク",
  "衣": "イ・ころも",
  "演": "エン",
  "煙": "エン・けむ(る)",
  "塩": "エン・しお",
  "押": "オウ・お(す)",
  "河": "カ・かわ",
  "灰": "カイ・はい",
  "干": "カン・ほ(す)",
  "甘": "カン・あま(い)",
  "汗": "カン・あせ",
  "幾": "キ・いく(つ)",
  "貴": "キ・たっと(い)",
  "疑": "ギ・うたが(う)",
  "儀": "ギ",
  "詰": "キツ・つ(める)",
  "逆": "ギャク・さか",
  "久": "キュウ・ひさ(しい)",
  "旧": "キュウ・ふる(い)",
  "巨": "キョ",
  "拠": "キョ・よ(る)",
  "拒": "キョ・こば(む)",
  "狭": "キョウ・せま(い)",
  "驚": "キョウ・おどろ(く)",
  "禁": "キン",
  "筋": "キン・すじ",
  "勤": "キン・つと(める)",
  "靴": "カ・くつ",
  "傾": "ケイ・かたむ(く)",
  "継": "ケイ・つ(ぐ)",
  "迎": "ゲイ・むか(える)",
  "撃": "ゲキ・う(つ)",
  "激": "ゲキ・はげ(しい)",
  "潔": "ケツ・いさぎよ(い)",
  "肩": "ケン・かた",
  "憲": "ケン",
  "賢": "ケン・かしこ(い)",
  "玄": "ゲン・くろ",
  "源": "ゲン・みなもと",
  "厳": "ゲン・おごそ(か)",
  "己": "コ・おのれ",
  "呼": "コ・よ(ぶ)",
  "誤": "ゴ・あやま(る)",
  "抗": "コウ・あらが(う)",
  "更": "コウ・さら",
  "硬": "コウ・かた(い)",
  "荒": "コウ・あ(らす)",
  "座": "ザ・すわ(る)",
  "再": "サイ・ふたた(び)",
  "咲": "ショウ・さ(く)",
  "撮": "サツ・と(る)",
  "参": "サン・まい(る)",
  "士": "シ・さむらい",
  "志": "シ・シリング",
  "枝": "シ・えだ",
  "飼": "シ・か(う)",
  "湿": "シツ・しめ(る)",
  "芝": "シ・しば",
  "捨": "シャ・す(てる)",
  "寂": "ジャク・さび",
  "若": "ジャク・わか(い)",
  "熟": "ジュク・う(れる)",
  "承": "ショウ・うけたまわ(る)",
  "昇": "ショウ・のぼ(る)",
  "松": "ショウ・まつ",
  "照": "ショウ・て(る)",
  "症": "ショウ",
  "障": "ショウ・さわ(る)",
  "詳": "ショウ・くわ(しい)",
  "丈": "ジョウ・たけ",
  "吹": "スイ・ふ(く)",
  "睡": "スイ・ねむ(る)",
  "省": "セイ・かえり(みる)",
  "勢": "セイ・いきお(い)",
  "誠": "セイ・まこと",
  "積": "セキ・つ(む)",
  "折": "セツ・お(る)",
  "占": "セン・し(める)",
  "宣": "セン・のたま(う)",
  "専": "セン・もっぱ(ら)",
  "泉": "セン・いずみ",
  "染": "セン・そ(める)",
  "倉": "ソウ・くら",
  "掃": "ソウ・は(く)",
  "替": "タイ・か(える)",
  "脱": "ダツ・ぬ(ぐ)",
  "端": "タン・はし",
  "誕": "タン",
  "団": "ダン・かたまり",
  "超": "チョウ・こ(える)",
  "敵": "テキ・かたき",
  "逃": "トウ・に(げる)"
}
